deeznutz/__init__.py
deeznutz/nutsclass.py
deeznutz/nutsfunctions.py
tests/__init__.py
tests/test_nutsfunctions.py
deeznutz-0.0.0.2.dist-info/LICENSE
deeznutz-0.0.0.2.dist-info/METADATA
deeznutz-0.0.0.2.dist-info/WHEEL
deeznutz-0.0.0.2.dist-info/top_level.txt
deeznutz-0.0.0.2.dist-info/RECORD
